odoo/addons/l10n_it_delivery_note/README.rst
odoo/addons/l10n_it_delivery_note/__init__.py
odoo/addons/l10n_it_delivery_note/__manifest__.py
odoo/addons/l10n_it_delivery_note/cli/__init__.py
odoo/addons/l10n_it_delivery_note/cli/core.py
odoo/addons/l10n_it_delivery_note/cli/migrate_l10n_it_ddt.py
odoo/addons/l10n_it_delivery_note/i18n/it.po
odoo/addons/l10n_it_delivery_note/i18n/l10n_it_delivery_note.pot
odoo/addons/l10n_it_delivery_note/mixins/__init__.py
odoo/addons/l10n_it_delivery_note/mixins/picking_checker.py
odoo/addons/l10n_it_delivery_note/mixins/shipping_updater.py
odoo/addons/l10n_it_delivery_note/models/__init__.py
odoo/addons/l10n_it_delivery_note/models/account_invoice.py
odoo/addons/l10n_it_delivery_note/models/res_company.py
odoo/addons/l10n_it_delivery_note/models/res_config_settings.py
odoo/addons/l10n_it_delivery_note/models/res_partner.py
odoo/addons/l10n_it_delivery_note/models/sale_order.py
odoo/addons/l10n_it_delivery_note/models/stock_delivery_note.py
odoo/addons/l10n_it_delivery_note/models/stock_picking.py
odoo/addons/l10n_it_delivery_note/readme/CONFIGURE.rst
odoo/addons/l10n_it_delivery_note/readme/CONTRIBUTORS.rst
odoo/addons/l10n_it_delivery_note/readme/DESCRIPTION.rst
odoo/addons/l10n_it_delivery_note/readme/USAGE.rst
odoo/addons/l10n_it_delivery_note/report/report_delivery_note.xml
odoo/addons/l10n_it_delivery_note/security/ir.model.access.csv
odoo/addons/l10n_it_delivery_note/security/ir_rule.xml
odoo/addons/l10n_it_delivery_note/security/res_groups.xml
odoo/addons/l10n_it_delivery_note/security/res_users.xml
odoo/addons/l10n_it_delivery_note/static/description/icon.jpg
odoo/addons/l10n_it_delivery_note/static/description/icon.png
odoo/addons/l10n_it_delivery_note/static/description/index.html
odoo/addons/l10n_it_delivery_note/static/src/scss/stock_delivery_note.scss
odoo/addons/l10n_it_delivery_note/tests/__init__.py
odoo/addons/l10n_it_delivery_note/tests/delivery_note_common.py
odoo12_addon_l10n_it_delivery_note-12.0.1.2.1.dist-info/METADATA
odoo12_addon_l10n_it_delivery_note-12.0.1.2.1.dist-info/WHEEL
odoo12_addon_l10n_it_delivery_note-12.0.1.2.1.dist-info/top_level.txt
odoo12_addon_l10n_it_delivery_note-12.0.1.2.1.dist-info/RECORD
