Metadata-Version: 2.1
Name: odoo12-addon-l10n-it-delivery-note
Version: 12.0.1.2.1
Summary: Crea, gestisce e fattura i DDT partendo dalle consegne
Home-page: https://github.com/OCA/l10n-italy/tree/12.0/l10n_it_delivery_note
Author: Marco Calcagni, Gianmarco Conte, Link IT Europe Srl, Odoo Community Association (OCA)
Author-email: support@odoo-community.org
License: AGPL-3
Platform: UNKNOWN
Classifier: Programming Language :: Python
Classifier: Framework :: Odoo
Classifier: Framework :: Odoo :: 12.0
Classifier: License :: OSI Approved :: GNU Affero General Public License v3
Requires-Python: >=3.5
Requires-Dist: odoo12-addon-l10n-it-delivery-note-base
Requires-Dist: odoo (<12.1dev,>=12.0a)
